custom_bar/__init__.py
custom_bar/bar_divider/__init__.py
custom_bar/bar_divider/gold_bar_divider/__init__.py
custom_bar/bar_divider/gold_bar_divider/gold_bar_divider.py
custom_bar/bar_divider/gold_bar_divider/gold_calc.py
custom_bar/bar_divider/gold_bar_divider/gold_models.py
custom_bar/bar_divider/price_bar_divider/__init__.py
custom_bar/bar_divider/price_bar_divider/price_bar_divider.py
custom_bar/converter/__init__.py
custom_bar/converter/bar_converter.py
custom_bar/converter/models.py
custom_bar/converter/protocols/__init__.py
custom_bar/converter/protocols/divider_protocol.py
custom_bar/demo.py
custom_stock_bar-0.1.2.dist-info/LICENSE
custom_stock_bar-0.1.2.dist-info/METADATA
custom_stock_bar-0.1.2.dist-info/WHEEL
custom_stock_bar-0.1.2.dist-info/RECORD
